AUTHORS.rst
CONTRIBUTING.rst
HISTORY.rst
LICENSE
MANIFEST.in
README.rst
setup.cfg
setup.py
Discord_AdvDB.egg-info/PKG-INFO
Discord_AdvDB.egg-info/SOURCES.txt
Discord_AdvDB.egg-info/dependency_links.txt
Discord_AdvDB.egg-info/not-zip-safe
Discord_AdvDB.egg-info/requires.txt
Discord_AdvDB.egg-info/top_level.txt
discord_advdb/__init__.py
discord_advdb/discord_advdb.py
discord_advdb.egg-info/PKG-INFO
discord_advdb.egg-info/SOURCES.txt
discord_advdb.egg-info/dependency_links.txt
discord_advdb.egg-info/not-zip-safe
discord_advdb.egg-info/requires.txt
discord_advdb.egg-info/top_level.txt
discord_advdb/modules/__init__.py
discord_advdb/modules/exceptions.py
docs/Makefile
docs/authors.rst
docs/conf.py
docs/contributing.rst
docs/history.rst
docs/index.rst
docs/installation.rst
docs/make.bat
docs/readme.rst
docs/usage.rst
tests/__init__.py
tests/test_discord_advdb.py