Metadata-Version: 1.2
Name: Discord-AdvDB
Version: 0.1.0
Summary: Advanced Database in discord
Home-page: https://github.com/CrAzyScreamx/Discord-AdvDB
Author: Amit Yanay
Author-email: amityanay5@gmail.com
License: GNU General Public License v3
Keywords: discord_advdb
Platform: UNKNOWN
Classifier: Development Status :: 2 - Pre-Alpha
Classifier: Intended Audience :: Developers
Classifier: License :: OSI Approved :: GNU General Public License v3 (GPLv3)
Classifier: Natural Language :: English
Classifier: Programming Language :: Python :: 3
Classifier: Programming Language :: Python :: 3.6
Classifier: Programming Language :: Python :: 3.7
Classifier: Programming Language :: Python :: 3.8
Requires-Python: >=3.6
